edashboards/__init__.py
edashboards/Release/smib_cffi.cp39-win_amd64.exp
edashboards/Release/smib_cffi.cp39-win_amd64.lib
edashboards/Release/smib_cffi.obj
edashboards/core/__init__.py
edashboards/core/db_emt_line_core.py
edashboards/core/grid_2bus4wire_hv.py
edashboards/core/grid_2bus4wire_hv_xy0.json
edashboards/core/grid_2bus4wire_lv.py
edashboards/core/grid_2bus4wire_lv_xy0.json
edashboards/core/grid_2bus4wire_mv.py
edashboards/core/grid_2bus4wire_mv_xy0.json
edashboards/core/grid_wind_farm.py
edashboards/core/im.py
edashboards/core/imib_fisix_3ord.py
edashboards/core/smib_milano_ex8p1_4ord.py
edashboards/core/smib_milano_ex8p1_4ord_avr.py
edashboards/core/smib/__init__.py
edashboards/core/smib/presentation.mplstyle
edashboards/core/smib/smib.json
edashboards/core/smib/smib_module.py
edashboards/core/smib/xy_0.json
edashboards/core/smib_avr/__init__.py
edashboards/core/smib_avr/presentation.mplstyle
edashboards/core/smib_avr/smib_avr_module.py
edashboards/core/smib_avr/xy_0.json
edashboards/core/trafo_shift/__init__.py
edashboards/core/trafo_shift/presentation.mplstyle
edashboards/core/trafo_shift/trafo_shift.json
edashboards/core/trafo_shift/trafo_shift.svg
edashboards/core/trafo_shift/trafo_shift_module.py
edashboards/core/trafo_shift/xy_0.json
edashboards/figures/dash_smib.svg
edashboards/figures/dash_smib_avr.svg
edashboards/figures/dash_smib_v2.svg
edashboards/figures/esquema_avr_gov_sm_carga.svg
edashboards/figures/imib.svg
edashboards-0.1.4.dist-info/LICENSE
edashboards-0.1.4.dist-info/WHEEL
edashboards-0.1.4.dist-info/METADATA
edashboards-0.1.4.dist-info/RECORD
