Metadata-Version: 2.1
Name: edashboards
Version: 0.1.4
Summary: Electric engineering dashboards
Author-email: Juan Manuel Mauricio <jmmauricio@us.es>
Classifier: License :: OSI Approved :: MIT License
Project-URL: Home, https://personal.us.es/jmmauricio/
